{
  "VORGANG": {
    "PLENUM": {
    },
    "SCHLAGWORT": [
      {
      },
      {
      }
    ],
    "ABSTRAKT": "Originaltext der Frage(n): \r\n \r\nInwieweit hat die Bundesregierung Hinweise über Gefechte einer Gruppe von ca. 600 islamistischen Kämpfern, welche der sog. Libysche Übergangsrat, der infolge des völkerrechtswidrigen Bombardements des UN-Mitgliedstaates Libyen durch die NATO installiert wurde, mit Kenntnis seines Vorsitzenden Mustafa Abd al-Dschalil illegal über die Türkei nach Syrien eingeschleust haben soll, um dort an bewaffneten Auseinandersetzungen gegen Staatspräsident Bashar al-Assad und einer weiteren Destabilisierung der Region teilzunehmen (siehe: http://rt.com/news/libya-syria-fighters-smuggled-475/)?"
  },
  "VORGANGSABLAUF": {
    "VORGANGSPOSITION": [
      {
      },
      {
        "PERSOENLICHER_URHEBER": [
          {
          },
          {
          }
        ]
      }
    ]
  }
}
